{
  "testfall_id": "TC067",
  "workflow": "ps",
  "score_strukturell": 1.0,
  "score_semantisch": 0.5361764705882354,
  "score_gesamt": 0.7217058823529412,
  "detail_strukturell": {
    "syntax_gate": 1,
    "fk_gate": 1,
    "pk_rate": 1.0,
    "pk_tabellen_gesamt": 18,
    "pk_tabellen_mit_pk": 18,
    "fk_referenzen_gesamt": 19,
    "fk_referenzen_ungueltig": 0
  },
  "detail_semantisch": {
    "entitaet": {
      "precision": 0.6111111111111112,
      "recall": 0.7857142857142857,
      "f1": 0.6875000000000001,
      "matched": 11,
      "nur_in_referenz": 3,
      "nur_in_generiert": 7
    },
    "attribut": {
      "precision": 0.5119047619047619,
      "recall": 0.5,
      "f1": 0.5058823529411764,
      "matched": 43,
      "nur_in_referenz": 43,
      "nur_in_generiert": 41
    },
    "beziehung": {
      "recall": 0.29411764705882354,
      "matched": 5,
      "nur_in_referenz": 12,
      "nur_in_generiert": 0
    }
  },
  "abweichungen": [
    {
      "element": "staff_members",
      "typ": "tabelle",
      "fehlerklasse": null
    },
    {
      "element": "care_cases",
      "typ": "tabelle",
      "fehlerklasse": null
    },
    {
      "element": "admissions",
      "typ": "tabelle",
      "fehlerklasse": null
    },
    {
      "element": "diagnoses.diagnosis_type",
      "typ": "attribut",
      "fehlerklasse": null
    },
    {
      "element": "diagnoses.documented_at",
      "typ": "attribut",
      "fehlerklasse": null
    },
    {
      "element": "departments.description",
      "typ": "attribut",
      "fehlerklasse": null
    },
    {
      "element": "medications.description",
      "typ": "attribut",
      "fehlerklasse": null
    },
    {
      "element": "procedures.primary_staff_member_id",
      "typ": "attribut",
      "fehlerklasse": null
    },
    {
      "element": "procedures.name",
      "typ": "attribut",
      "fehlerklasse": null
    },
    {
      "element": "procedures.procedure_timestamp",
      "typ": "attribut",
      "fehlerklasse": null
    },
    {
      "element": "procedures.notes",
      "typ": "attribut",
      "fehlerklasse": null
    },
    {
      "element": "contact_persons.firstname",
      "typ": "attribut",
      "fehlerklasse": null
    },
    {
      "element": "contact_persons.lastname",
      "typ": "attribut",
      "fehlerklasse": null
    },
    {
      "element": "contact_persons.relationship_type",
      "typ": "attribut",
      "fehlerklasse": null
    },
    {
      "element": "contact_persons.is_primary",
      "typ": "attribut",
      "fehlerklasse": null
    },
    {
      "element": "appointments.staff_member_id",
      "typ": "attribut",
      "fehlerklasse": null
    },
    {
      "element": "appointments.department_id",
      "typ": "attribut",
      "fehlerklasse": null
    },
    {
      "element": "appointments.notes",
      "typ": "attribut",
      "fehlerklasse": null
    },
    {
      "element": "patients.insurance_provider_id",
      "typ": "attribut",
      "fehlerklasse": null
    },
    {
      "element": "patients.insurance_number",
      "typ": "attribut",
      "fehlerklasse": null
    },
    {
      "element": "prescriptions.prescribing_staff_member_id",
      "typ": "attribut",
      "fehlerklasse": null
    },
    {
      "element": "prescriptions.notes",
      "typ": "attribut",
      "fehlerklasse": null
    },
    {
      "element": "staff_members_stations.id",
      "typ": "attribut",
      "fehlerklasse": null
    },
    {
      "element": "staff_members_stations.assignment_role",
      "typ": "attribut",
      "fehlerklasse": null
    },
    {
      "element": "staff_members_stations.startdate",
      "typ": "attribut",
      "fehlerklasse": null
    },
    {
      "element": "staff_members_stations.enddate",
      "typ": "attribut",
      "fehlerklasse": null
    },
    {
      "element": "staff_members.id",
      "typ": "attribut",
      "fehlerklasse": null
    },
    {
      "element": "staff_members.firstname",
      "typ": "attribut",
      "fehlerklasse": null
    },
    {
      "element": "staff_members.lastname",
      "typ": "attribut",
      "fehlerklasse": null
    },
    {
      "element": "staff_members.staff_type",
      "typ": "attribut",
      "fehlerklasse": null
    },
    {
      "element": "staff_members.specialty",
      "typ": "attribut",
      "fehlerklasse": null
    },
    {
      "element": "staff_members.phone",
      "typ": "attribut",
      "fehlerklasse": null
    },
    {
      "element": "staff_members.email",
      "typ": "attribut",
      "fehlerklasse": null
    },
    {
      "element": "staff_members.is_active",
      "typ": "attribut",
      "fehlerklasse": null
    },
    {
      "element": "care_cases.id",
      "typ": "attribut",
      "fehlerklasse": null
    },
    {
      "element": "care_cases.patient_id",
      "typ": "attribut",
      "fehlerklasse": null
    },
    {
      "element": "care_cases.case_type",
      "typ": "attribut",
      "fehlerklasse": null
    },
    {
      "element": "care_cases.admissiondate",
      "typ": "attribut",
      "fehlerklasse": null
    },
    {
      "element": "care_cases.dischargedate",
      "typ": "attribut",
      "fehlerklasse": null
    },
    {
      "element": "care_cases.status",
      "typ": "attribut",
      "fehlerklasse": null
    },
    {
      "element": "care_cases.referring_physician",
      "typ": "attribut",
      "fehlerklasse": null
    },
    {
      "element": "admissions.id",
      "typ": "attribut",
      "fehlerklasse": null
    },
    {
      "element": "admissions.care_case_id",
      "typ": "attribut",
      "fehlerklasse": null
    },
    {
      "element": "admissions.station_id",
      "typ": "attribut",
      "fehlerklasse": null
    },
    {
      "element": "admissions.admission_timestamp",
      "typ": "attribut",
      "fehlerklasse": null
    },
    {
      "element": "admissions.discharge_timestamp",
      "typ": "attribut",
      "fehlerklasse": null
    },
    {
      "element": "admissions → care_cases",
      "typ": "beziehung",
      "fehlerklasse": null
    },
    {
      "element": "admissions → stations",
      "typ": "beziehung",
      "fehlerklasse": null
    },
    {
      "element": "appointments → departments",
      "typ": "beziehung",
      "fehlerklasse": null
    },
    {
      "element": "appointments → staff_members",
      "typ": "beziehung",
      "fehlerklasse": null
    },
    {
      "element": "care_cases → patients",
      "typ": "beziehung",
      "fehlerklasse": null
    },
    {
      "element": "diagnoses → care_cases",
      "typ": "beziehung",
      "fehlerklasse": null
    },
    {
      "element": "patients → insurance_providers",
      "typ": "beziehung",
      "fehlerklasse": null
    },
    {
      "element": "prescriptions → care_cases",
      "typ": "beziehung",
      "fehlerklasse": null
    },
    {
      "element": "prescriptions → staff_members",
      "typ": "beziehung",
      "fehlerklasse": null
    },
    {
      "element": "procedures → care_cases",
      "typ": "beziehung",
      "fehlerklasse": null
    },
    {
      "element": "procedures → staff_members",
      "typ": "beziehung",
      "fehlerklasse": null
    },
    {
      "element": "staff_members_stations → staff_members",
      "typ": "beziehung",
      "fehlerklasse": null
    }
  ],
  "state": {
    "anforderungstext": "In unserem Krankenhaus sollen die wichtigsten Abläufe rund um stationäre und ambulante Behandlungen nachvollziehbar sein. Erfasst werden müssen die Patientinnen und Patienten mit ihren Stammdaten, Kontaktmöglichkeiten und – soweit bekannt – einer zuständigen Bezugsperson. Bei Minderjährigen oder nicht ansprechbaren Personen kann das wichtig sein, aber nicht immer liegt alles vollständig vor. Außerdem soll sichtbar sein, bei welcher Krankenkasse jemand versichert ist; manche Fälle sind jedoch privat oder die Versicherung ändert sich mitten im Jahr.\n\nFür die medizinische Versorgung brauchen wir die behandelnden Ärztinnen und Ärzte mit Fachrichtung, sowie das Pflegepersonal auf den Stationen. Nicht ganz klar ist, ob Beschäftigte immer genau einer Station fest zugeordnet sind, weil sie manchmal aushelfen. Stationen gehören zu einem Fachbereich wie Kardiologie, Chirurgie oder Neurologie und haben eine bestimmte Bettenkapazität. Patientinnen und Patienten können aufgenommen, verlegt und entlassen werden. Dabei sollte man sehen, auf welcher Station sie wann lagen; bei kurzen Aufenthalten ist die Uhrzeit relevant, meistens reicht aber das Datum. Ob ein Aufenthalt ohne vorherige Aufnahme vorkommen darf, müsste man im Zweifel offenlassen.\n\nZu jedem Behandlungsfall können Diagnosen dokumentiert werden, idealerweise mit ICD-Code und Freitext. Ebenso sollen Prozeduren bzw. Eingriffe mit OPS-Bezug festgehalten werden. Ein Eingriff wird von einer Ärztin oder einem Arzt durchgeführt, oft mit Assistenz, manchmal aber auch mit einem ganzen Team; für den Anfang reicht vielleicht die hauptverantwortliche Person. Medikamente sollen verordnet werden mit Dosierung, Start und Ende. Unklar ist, ob dieselbe Verordnung mehrfach angepasst wird oder ob jede Änderung als neuer Eintrag gilt.\n\nWichtig sind auch Termine im ambulanten Bereich, zum Beispiel in der Sprechstunde oder Nachsorge. Ein Termin kann ausfallen oder verschoben werden. Laboruntersuchungen wären später interessant, müssen aber jetzt noch nicht im Detail abgebildet werden.",
    "workflow_name": "ps",
    "logical_schema": {
      "tables": [
        {
          "name": "patients",
          "columns": [
            {
              "name": "id",
              "type": "INTEGER",
              "primary_key": true,
              "nullable": false
            },
            {
              "name": "firstname",
              "type": "VARCHAR",
              "primary_key": false,
              "nullable": false
            },
            {
              "name": "lastname",
              "type": "VARCHAR",
              "primary_key": false,
              "nullable": false
            },
            {
              "name": "birthdate",
              "type": "DATE",
              "primary_key": false,
              "nullable": false
            },
            {
              "name": "gender",
              "type": "VARCHAR",
              "primary_key": false,
              "nullable": true
            },
            {
              "name": "address",
              "type": "VARCHAR",
              "primary_key": false,
              "nullable": true
            },
            {
              "name": "phone",
              "type": "VARCHAR",
              "primary_key": false,
              "nullable": true
            },
            {
              "name": "email",
              "type": "VARCHAR",
              "primary_key": false,
              "nullable": true
            }
          ],
          "foreign_keys": []
        },
        {
          "name": "contact_persons",
          "columns": [
            {
              "name": "id",
              "type": "INTEGER",
              "primary_key": true,
              "nullable": false
            },
            {
              "name": "patient_id",
              "type": "INTEGER",
              "primary_key": false,
              "nullable": false
            },
            {
              "name": "name",
              "type": "VARCHAR",
              "primary_key": false,
              "nullable": false
            },
            {
              "name": "relationship",
              "type": "VARCHAR",
              "primary_key": false,
              "nullable": true
            },
            {
              "name": "phone",
              "type": "VARCHAR",
              "primary_key": false,
              "nullable": true
            },
            {
              "name": "email",
              "type": "VARCHAR",
              "primary_key": false,
              "nullable": true
            }
          ],
          "foreign_keys": [
            {
              "from_column": "patient_id",
              "references_table": "patients",
              "references_column": "id"
            }
          ]
        },
        {
          "name": "insurance_companies",
          "columns": [
            {
              "name": "id",
              "type": "INTEGER",
              "primary_key": true,
              "nullable": false
            },
            {
              "name": "name",
              "type": "VARCHAR",
              "primary_key": false,
              "nullable": false
            },
            {
              "name": "insurance_type",
              "type": "VARCHAR",
              "primary_key": false,
              "nullable": true
            }
          ],
          "foreign_keys": []
        },
        {
          "name": "insurances",
          "columns": [
            {
              "name": "id",
              "type": "INTEGER",
              "primary_key": true,
              "nullable": false
            },
            {
              "name": "patient_id",
              "type": "INTEGER",
              "primary_key": false,
              "nullable": false
            },
            {
              "name": "insurance_company_id",
              "type": "INTEGER",
              "primary_key": false,
              "nullable": true
            },
            {
              "name": "startdate",
              "type": "DATE",
              "primary_key": false,
              "nullable": false
            },
            {
              "name": "enddate",
              "type": "DATE",
              "primary_key": false,
              "nullable": true
            },
            {
              "name": "insurance_type",
              "type": "VARCHAR",
              "primary_key": false,
              "nullable": false
            }
          ],
          "foreign_keys": [
            {
              "from_column": "patient_id",
              "references_table": "patients",
              "references_column": "id"
            },
            {
              "from_column": "insurance_company_id",
              "references_table": "insurance_companies",
              "references_column": "id"
            }
          ]
        },
        {
          "name": "departments",
          "columns": [
            {
              "name": "id",
              "type": "INTEGER",
              "primary_key": true,
              "nullable": false
            },
            {
              "name": "name",
              "type": "VARCHAR",
              "primary_key": false,
              "nullable": false
            }
          ],
          "foreign_keys": []
        },
        {
          "name": "stations",
          "columns": [
            {
              "name": "id",
              "type": "INTEGER",
              "primary_key": true,
              "nullable": false
            },
            {
              "name": "name",
              "type": "VARCHAR",
              "primary_key": false,
              "nullable": false
            },
            {
              "name": "department_id",
              "type": "INTEGER",
              "primary_key": false,
              "nullable": false
            },
            {
              "name": "bed_capacity",
              "type": "INTEGER",
              "primary_key": false,
              "nullable": false
            }
          ],
          "foreign_keys": [
            {
              "from_column": "department_id",
              "references_table": "departments",
              "references_column": "id"
            }
          ]
        },
        {
          "name": "physicians",
          "columns": [
            {
              "name": "id",
              "type": "INTEGER",
              "primary_key": true,
              "nullable": false
            },
            {
              "name": "firstname",
              "type": "VARCHAR",
              "primary_key": false,
              "nullable": false
            },
            {
              "name": "lastname",
              "type": "VARCHAR",
              "primary_key": false,
              "nullable": false
            },
            {
              "name": "specialization",
              "type": "VARCHAR",
              "primary_key": false,
              "nullable": false
            }
          ],
          "foreign_keys": []
        },
        {
          "name": "nursing_staff",
          "columns": [
            {
              "name": "id",
              "type": "INTEGER",
              "primary_key": true,
              "nullable": false
            },
            {
              "name": "firstname",
              "type": "VARCHAR",
              "primary_key": false,
              "nullable": false
            },
            {
              "name": "lastname",
              "type": "VARCHAR",
              "primary_key": false,
              "nullable": false
            }
          ],
          "foreign_keys": []
        },
        {
          "name": "stays",
          "columns": [
            {
              "name": "id",
              "type": "INTEGER",
              "primary_key": true,
              "nullable": false
            },
            {
              "name": "patient_id",
              "type": "INTEGER",
              "primary_key": false,
              "nullable": false
            },
            {
              "name": "admission_date",
              "type": "DATE",
              "primary_key": false,
              "nullable": false
            },
            {
              "name": "admission_time",
              "type": "VARCHAR",
              "primary_key": false,
              "nullable": true
            },
            {
              "name": "discharge_date",
              "type": "DATE",
              "primary_key": false,
              "nullable": true
            },
            {
              "name": "discharge_time",
              "type": "VARCHAR",
              "primary_key": false,
              "nullable": true
            }
          ],
          "foreign_keys": [
            {
              "from_column": "patient_id",
              "references_table": "patients",
              "references_column": "id"
            }
          ]
        },
        {
          "name": "station_stays",
          "columns": [
            {
              "name": "id",
              "type": "INTEGER",
              "primary_key": true,
              "nullable": false
            },
            {
              "name": "stay_id",
              "type": "INTEGER",
              "primary_key": false,
              "nullable": false
            },
            {
              "name": "station_id",
              "type": "INTEGER",
              "primary_key": false,
              "nullable": false
            },
            {
              "name": "start_date",
              "type": "DATE",
              "primary_key": false,
              "nullable": false
            },
            {
              "name": "start_time",
              "type": "VARCHAR",
              "primary_key": false,
              "nullable": true
            },
            {
              "name": "end_date",
              "type": "DATE",
              "primary_key": false,
              "nullable": true
            },
            {
              "name": "end_time",
              "type": "VARCHAR",
              "primary_key": false,
              "nullable": true
            }
          ],
          "foreign_keys": [
            {
              "from_column": "stay_id",
              "references_table": "stays",
              "references_column": "id"
            },
            {
              "from_column": "station_id",
              "references_table": "stations",
              "references_column": "id"
            }
          ]
        },
        {
          "name": "treatment_cases",
          "columns": [
            {
              "name": "id",
              "type": "INTEGER",
              "primary_key": true,
              "nullable": false
            },
            {
              "name": "patient_id",
              "type": "INTEGER",
              "primary_key": false,
              "nullable": false
            },
            {
              "name": "stay_id",
              "type": "INTEGER",
              "primary_key": false,
              "nullable": true
            },
            {
              "name": "startdate",
              "type": "DATE",
              "primary_key": false,
              "nullable": false
            },
            {
              "name": "enddate",
              "type": "DATE",
              "primary_key": false,
              "nullable": true
            }
          ],
          "foreign_keys": [
            {
              "from_column": "patient_id",
              "references_table": "patients",
              "references_column": "id"
            },
            {
              "from_column": "stay_id",
              "references_table": "stays",
              "references_column": "id"
            }
          ]
        },
        {
          "name": "diagnoses",
          "columns": [
            {
              "name": "id",
              "type": "INTEGER",
              "primary_key": true,
              "nullable": false
            },
            {
              "name": "treatment_case_id",
              "type": "INTEGER",
              "primary_key": false,
              "nullable": false
            },
            {
              "name": "icd_code",
              "type": "VARCHAR",
              "primary_key": false,
              "nullable": true
            },
            {
              "name": "description",
              "type": "TEXT",
              "primary_key": false,
              "nullable": true
            }
          ],
          "foreign_keys": [
            {
              "from_column": "treatment_case_id",
              "references_table": "treatment_cases",
              "references_column": "id"
            }
          ]
        },
        {
          "name": "procedures",
          "columns": [
            {
              "name": "id",
              "type": "INTEGER",
              "primary_key": true,
              "nullable": false
            },
            {
              "name": "treatment_case_id",
              "type": "INTEGER",
              "primary_key": false,
              "nullable": false
            },
            {
              "name": "physician_id",
              "type": "INTEGER",
              "primary_key": false,
              "nullable": false
            },
            {
              "name": "ops_code",
              "type": "VARCHAR",
              "primary_key": false,
              "nullable": true
            },
            {
              "name": "description",
              "type": "TEXT",
              "primary_key": false,
              "nullable": true
            },
            {
              "name": "execution_date",
              "type": "DATE",
              "primary_key": false,
              "nullable": false
            },
            {
              "name": "execution_time",
              "type": "VARCHAR",
              "primary_key": false,
              "nullable": true
            }
          ],
          "foreign_keys": [
            {
              "from_column": "treatment_case_id",
              "references_table": "treatment_cases",
              "references_column": "id"
            },
            {
              "from_column": "physician_id",
              "references_table": "physicians",
              "references_column": "id"
            }
          ]
        },
        {
          "name": "medications",
          "columns": [
            {
              "name": "id",
              "type": "INTEGER",
              "primary_key": true,
              "nullable": false
            },
            {
              "name": "name",
              "type": "VARCHAR",
              "primary_key": false,
              "nullable": false
            },
            {
              "name": "active_ingredient",
              "type": "VARCHAR",
              "primary_key": false,
              "nullable": true
            }
          ],
          "foreign_keys": []
        },
        {
          "name": "medication_prescriptions",
          "columns": [
            {
              "name": "id",
              "type": "INTEGER",
              "primary_key": true,
              "nullable": false
            },
            {
              "name": "treatment_case_id",
              "type": "INTEGER",
              "primary_key": false,
              "nullable": false
            },
            {
              "name": "medication_id",
              "type": "INTEGER",
              "primary_key": false,
              "nullable": false
            },
            {
              "name": "dosage",
              "type": "VARCHAR",
              "primary_key": false,
              "nullable": false
            },
            {
              "name": "startdate",
              "type": "DATE",
              "primary_key": false,
              "nullable": false
            },
            {
              "name": "enddate",
              "type": "DATE",
              "primary_key": false,
              "nullable": true
            }
          ],
          "foreign_keys": [
            {
              "from_column": "treatment_case_id",
              "references_table": "treatment_cases",
              "references_column": "id"
            },
            {
              "from_column": "medication_id",
              "references_table": "medications",
              "references_column": "id"
            }
          ]
        },
        {
          "name": "appointments",
          "columns": [
            {
              "name": "id",
              "type": "INTEGER",
              "primary_key": true,
              "nullable": false
            },
            {
              "name": "patient_id",
              "type": "INTEGER",
              "primary_key": false,
              "nullable": false
            },
            {
              "name": "appointment_date",
              "type": "DATE",
              "primary_key": false,
              "nullable": false
            },
            {
              "name": "appointment_time",
              "type": "VARCHAR",
              "primary_key": false,
              "nullable": false
            },
            {
              "name": "appointment_type",
              "type": "VARCHAR",
              "primary_key": false,
              "nullable": false
            },
            {
              "name": "status",
              "type": "VARCHAR",
              "primary_key": false,
              "nullable": false
            }
          ],
          "foreign_keys": [
            {
              "from_column": "patient_id",
              "references_table": "patients",
              "references_column": "id"
            }
          ]
        },
        {
          "name": "patient_physicians",
          "columns": [
            {
              "name": "patient_id",
              "type": "INTEGER",
              "primary_key": true,
              "nullable": false
            },
            {
              "name": "physician_id",
              "type": "INTEGER",
              "primary_key": true,
              "nullable": false
            }
          ],
          "foreign_keys": [
            {
              "from_column": "patient_id",
              "references_table": "patients",
              "references_column": "id"
            },
            {
              "from_column": "physician_id",
              "references_table": "physicians",
              "references_column": "id"
            }
          ]
        },
        {
          "name": "nursing_staff_stations",
          "columns": [
            {
              "name": "nursing_staff_id",
              "type": "INTEGER",
              "primary_key": true,
              "nullable": false
            },
            {
              "name": "station_id",
              "type": "INTEGER",
              "primary_key": true,
              "nullable": false
            }
          ],
          "foreign_keys": [
            {
              "from_column": "nursing_staff_id",
              "references_table": "nursing_staff",
              "references_column": "id"
            },
            {
              "from_column": "station_id",
              "references_table": "stations",
              "references_column": "id"
            }
          ]
        }
      ]
    },
    "requirements_report": {
      "entitaeten": [
        {
          "name": "Patient",
          "attribute": [
            "PatientenID",
            "Vorname",
            "Nachname",
            "Stammdaten",
            "Kontaktmöglichkeiten",
            "Geburtsdatum",
            "Geschlecht"
          ],
          "beschreibung": "Patientinnen und Patienten mit ihren Stammdaten und Kontaktmöglichkeiten"
        },
        {
          "name": "Bezugsperson",
          "attribute": [
            "BezugspersonID",
            "Name",
            "Kontaktmöglichkeiten",
            "Beziehung zum Patienten"
          ],
          "beschreibung": "Zuständige Bezugsperson für Patienten, besonders relevant bei Minderjährigen oder nicht ansprechbaren Personen"
        },
        {
          "name": "Krankenkasse",
          "attribute": [
            "KrankenkassenID",
            "Name",
            "Versicherungstyp"
          ],
          "beschreibung": "Krankenkasse, bei der ein Patient versichert ist"
        },
        {
          "name": "Versicherung",
          "attribute": [
            "VersicherungsID",
            "PatientenID",
            "KrankenkassenID",
            "Startdatum",
            "Enddatum",
            "Versicherungstyp"
          ],
          "beschreibung": "Versicherungsverhältnis eines Patienten, kann sich im Laufe des Jahres ändern oder privat sein"
        },
        {
          "name": "Arzt",
          "attribute": [
            "ArztID",
            "Vorname",
            "Nachname",
            "Fachrichtung"
          ],
          "beschreibung": "Behandelnde Ärztinnen und Ärzte mit Fachrichtung"
        },
        {
          "name": "Pflegepersonal",
          "attribute": [
            "PersonalID",
            "Vorname",
            "Nachname"
          ],
          "beschreibung": "Pflegepersonal auf den Stationen"
        },
        {
          "name": "Station",
          "attribute": [
            "StationsID",
            "Name",
            "Fachbereich",
            "Bettenkapazität"
          ],
          "beschreibung": "Stationen gehören zu einem Fachbereich und haben eine bestimmte Bettenkapazität"
        },
        {
          "name": "Fachbereich",
          "attribute": [
            "FachbereichID",
            "Name"
          ],
          "beschreibung": "Fachbereiche wie Kardiologie, Chirurgie oder Neurologie"
        },
        {
          "name": "Aufenthalt",
          "attribute": [
            "AufenthaltID",
            "PatientenID",
            "Aufnahmedatum",
            "Aufnahmeuhrzeit",
            "Entlassungsdatum",
            "Entlassungsuhrzeit"
          ],
          "beschreibung": "Stationärer Aufenthalt eines Patienten mit Aufnahme, Verlegung und Entlassung"
        },
        {
          "name": "Stationsaufenthalt",
          "attribute": [
            "StationsaufenthaltID",
            "AufenthaltID",
            "StationsID",
            "Anfangsdatum",
            "Anfangsuhrzeit",
            "Enddatum",
            "Enduhrzeit"
          ],
          "beschreibung": "Zeitraum, in dem ein Patient auf einer bestimmten Station lag"
        },
        {
          "name": "Behandlungsfall",
          "attribute": [
            "BehandlungsfallID",
            "PatientenID",
            "AufenthaltID",
            "Startdatum",
            "Enddatum"
          ],
          "beschreibung": "Behandlungsfall mit zugehörigen Diagnosen, Prozeduren und Medikamenten"
        },
        {
          "name": "Diagnose",
          "attribute": [
            "DiagnoseID",
            "BehandlungsfallID",
            "ICD-Code",
            "Freitext"
          ],
          "beschreibung": "Diagnose zu einem Behandlungsfall mit ICD-Code und Freitext"
        },
        {
          "name": "Prozedur",
          "attribute": [
            "ProzedurID",
            "BehandlungsfallID",
            "OPS-Code",
            "Beschreibung",
            "Durchführungsdatum",
            "Durchführungsuhrzeit"
          ],
          "beschreibung": "Eingriff oder Prozedur mit OPS-Bezug"
        },
        {
          "name": "Medikament",
          "attribute": [
            "MedikamentID",
            "Name",
            "Wirkstoff"
          ],
          "beschreibung": "Medikament mit Wirkstoff"
        },
        {
          "name": "Medikamentenverordnung",
          "attribute": [
            "VerordnungsID",
            "BehandlungsfallID",
            "MedikamentID",
            "Dosierung",
            "Startdatum",
            "Enddatum"
          ],
          "beschreibung": "Verordnung eines Medikaments mit Dosierung, Start und Ende"
        },
        {
          "name": "Termin",
          "attribute": [
            "TerminID",
            "PatientenID",
            "Datum",
            "Uhrzeit",
            "Termintyp",
            "Status"
          ],
          "beschreibung": "Termin im ambulanten Bereich wie Sprechstunde oder Nachsorge, kann ausfallen oder verschoben werden"
        }
      ],
      "beziehungen": [
        {
          "von": "Patient",
          "zu": "Bezugsperson",
          "kardinalitaet": "1:0..1",
          "beschreibung": "Ein Patient kann eine zuständige Bezugsperson haben (optional, besonders bei Minderjährigen)"
        },
        {
          "von": "Patient",
          "zu": "Versicherung",
          "kardinalitaet": "1:N",
          "beschreibung": "Ein Patient kann mehrere Versicherungsverhältnisse haben (Wechsel im Jahr möglich)"
        },
        {
          "von": "Versicherung",
          "zu": "Krankenkasse",
          "kardinalitaet": "N:1",
          "beschreibung": "Eine Versicherung bezieht sich auf eine Krankenkasse"
        },
        {
          "von": "Patient",
          "zu": "Aufenthalt",
          "kardinalitaet": "1:N",
          "beschreibung": "Ein Patient kann mehrere stationäre Aufenthalte haben"
        },
        {
          "von": "Aufenthalt",
          "zu": "Stationsaufenthalt",
          "kardinalitaet": "1:N",
          "beschreibung": "Ein Aufenthalt kann mehrere Stationsaufenthalte umfassen (Verlegungen)"
        },
        {
          "von": "Stationsaufenthalt",
          "zu": "Station",
          "kardinalitaet": "N:1",
          "beschreibung": "Ein Stationsaufenthalt bezieht sich auf eine Station"
        },
        {
          "von": "Station",
          "zu": "Fachbereich",
          "kardinalitaet": "N:1",
          "beschreibung": "Eine Station gehört zu einem Fachbereich"
        },
        {
          "von": "Pflegepersonal",
          "zu": "Station",
          "kardinalitaet": "N:N",
          "beschreibung": "Pflegepersonal kann auf einer oder mehreren Stationen arbeiten (Aushilfen möglich)"
        },
        {
          "von": "Patient",
          "zu": "Behandlungsfall",
          "kardinalitaet": "1:N",
          "beschreibung": "Ein Patient kann mehrere Behandlungsfälle haben"
        },
        {
          "von": "Aufenthalt",
          "zu": "Behandlungsfall",
          "kardinalitaet": "1:N",
          "beschreibung": "Ein Aufenthalt kann mehrere Behandlungsfälle umfassen"
        },
        {
          "von": "Behandlungsfall",
          "zu": "Diagnose",
          "kardinalitaet": "1:N",
          "beschreibung": "Ein Behandlungsfall kann mehrere Diagnosen haben"
        },
        {
          "von": "Behandlungsfall",
          "zu": "Prozedur",
          "kardinalitaet": "1:N",
          "beschreibung": "Ein Behandlungsfall kann mehrere Prozeduren/Eingriffe haben"
        },
        {
          "von": "Prozedur",
          "zu": "Arzt",
          "kardinalitaet": "N:1",
          "beschreibung": "Eine Prozedur wird von einer hauptverantwortlichen Ärztin oder einem Arzt durchgeführt"
        },
        {
          "von": "Behandlungsfall",
          "zu": "Medikamentenverordnung",
          "kardinalitaet": "1:N",
          "beschreibung": "Ein Behandlungsfall kann mehrere Medikamentenverordnungen haben"
        },
        {
          "von": "Medikamentenverordnung",
          "zu": "Medikament",
          "kardinalitaet": "N:1",
          "beschreibung": "Eine Medikamentenverordnung bezieht sich auf ein Medikament"
        },
        {
          "von": "Patient",
          "zu": "Termin",
          "kardinalitaet": "1:N",
          "beschreibung": "Ein Patient kann mehrere ambulante Termine haben"
        },
        {
          "von": "Patient",
          "zu": "Arzt",
          "kardinalitaet": "N:N",
          "beschreibung": "Ein Patient kann von mehreren Ärzten behandelt werden, ein Arzt behandelt mehrere Patienten"
        }
      ],
      "unklarheiten": [
        {
          "beschreibung": "Ist die Erfassung von Bezugspersonen obligatorisch oder optional? Der Text sagt 'nicht immer liegt alles vollständig vor'.",
          "betroffene_elemente": [
            "Bezugsperson",
            "Patient"
          ]
        },
        {
          "beschreibung": "Wie wird mit privaten Versicherungen oder fehlenden Versicherungsinformationen umgegangen? Ist eine Krankenkasse immer erforderlich?",
          "betroffene_elemente": [
            "Versicherung",
            "Krankenkasse"
          ]
        },
        {
          "beschreibung": "Sind Beschäftigte (Ärzte und Pflegepersonal) immer genau einer Station zugeordnet oder können sie mehreren Stationen zugeordnet sein (Aushilfen)?",
          "betroffene_elemente": [
            "Pflegepersonal",
            "Station",
            "Arzt"
          ]
        },
        {
          "beschreibung": "Darf ein Aufenthalt ohne vorherige Aufnahme vorkommen? Ist die Aufnahme immer erforderlich?",
          "betroffene_elemente": [
            "Aufenthalt",
            "Stationsaufenthalt"
          ]
        },
        {
          "beschreibung": "Wird dieselbe Medikamentenverordnung mehrfach angepasst (Update) oder gilt jede Änderung als neuer Eintrag?",
          "betroffene_elemente": [
            "Medikamentenverordnung"
          ]
        },
        {
          "beschreibung": "Wie wird die Assistenz bei Prozeduren/Eingriffen abgebildet? Reicht die hauptverantwortliche Person oder sollen alle beteiligten Personen erfasst werden?",
          "betroffene_elemente": [
            "Prozedur",
            "Arzt",
            "Pflegepersonal"
          ]
        },
        {
          "beschreibung": "Ist die Erfassung von Uhrzeit bei Aufenthalten und Stationsaufenthalten immer erforderlich oder nur bei kurzen Aufenthalten?",
          "betroffene_elemente": [
            "Aufenthalt",
            "Stationsaufenthalt"
          ]
        },
        {
          "beschreibung": "Welche Stammdaten und Kontaktmöglichkeiten sind konkret erforderlich? (z.B. Adresse, Telefon, E-Mail)",
          "betroffene_elemente": [
            "Patient",
            "Bezugsperson"
          ]
        }
      ]
    },
    "er_modell": {
      "entitaeten": [
        {
          "name": "Patient",
          "attribute": [
            {
              "name": "PatientenID",
              "datentyp": "INTEGER",
              "primaerschluessel": true,
              "pflichtfeld": true
            },
            {
              "name": "Vorname",
              "datentyp": "VARCHAR",
              "primaerschluessel": false,
              "pflichtfeld": true
            },
            {
              "name": "Nachname",
              "datentyp": "VARCHAR",
              "primaerschluessel": false,
              "pflichtfeld": true
            },
            {
              "name": "Geburtsdatum",
              "datentyp": "DATE",
              "primaerschluessel": false,
              "pflichtfeld": true
            },
            {
              "name": "Geschlecht",
              "datentyp": "VARCHAR",
              "primaerschluessel": false,
              "pflichtfeld": false
            },
            {
              "name": "Adresse",
              "datentyp": "VARCHAR",
              "primaerschluessel": false,
              "pflichtfeld": false
            },
            {
              "name": "Telefon",
              "datentyp": "VARCHAR",
              "primaerschluessel": false,
              "pflichtfeld": false
            },
            {
              "name": "EMail",
              "datentyp": "VARCHAR",
              "primaerschluessel": false,
              "pflichtfeld": false
            }
          ]
        },
        {
          "name": "Bezugsperson",
          "attribute": [
            {
              "name": "BezugspersonID",
              "datentyp": "INTEGER",
              "primaerschluessel": true,
              "pflichtfeld": true
            },
            {
              "name": "PatientenID",
              "datentyp": "INTEGER",
              "primaerschluessel": false,
              "pflichtfeld": true
            },
            {
              "name": "Name",
              "datentyp": "VARCHAR",
              "primaerschluessel": false,
              "pflichtfeld": true
            },
            {
              "name": "Beziehung",
              "datentyp": "VARCHAR",
              "primaerschluessel": false,
              "pflichtfeld": false
            },
            {
              "name": "Telefon",
              "datentyp": "VARCHAR",
              "primaerschluessel": false,
              "pflichtfeld": false
            },
            {
              "name": "EMail",
              "datentyp": "VARCHAR",
              "primaerschluessel": false,
              "pflichtfeld": false
            }
          ]
        },
        {
          "name": "Krankenkasse",
          "attribute": [
            {
              "name": "KrankenkassenID",
              "datentyp": "INTEGER",
              "primaerschluessel": true,
              "pflichtfeld": true
            },
            {
              "name": "Name",
              "datentyp": "VARCHAR",
              "primaerschluessel": false,
              "pflichtfeld": true
            },
            {
              "name": "Versicherungstyp",
              "datentyp": "VARCHAR",
              "primaerschluessel": false,
              "pflichtfeld": false
            }
          ]
        },
        {
          "name": "Versicherung",
          "attribute": [
            {
              "name": "VersicherungsID",
              "datentyp": "INTEGER",
              "primaerschluessel": true,
              "pflichtfeld": true
            },
            {
              "name": "PatientenID",
              "datentyp": "INTEGER",
              "primaerschluessel": false,
              "pflichtfeld": true
            },
            {
              "name": "KrankenkassenID",
              "datentyp": "INTEGER",
              "primaerschluessel": false,
              "pflichtfeld": false
            },
            {
              "name": "Startdatum",
              "datentyp": "DATE",
              "primaerschluessel": false,
              "pflichtfeld": true
            },
            {
              "name": "Enddatum",
              "datentyp": "DATE",
              "primaerschluessel": false,
              "pflichtfeld": false
            },
            {
              "name": "Versicherungstyp",
              "datentyp": "VARCHAR",
              "primaerschluessel": false,
              "pflichtfeld": true
            }
          ]
        },
        {
          "name": "Fachbereich",
          "attribute": [
            {
              "name": "FachbereichID",
              "datentyp": "INTEGER",
              "primaerschluessel": true,
              "pflichtfeld": true
            },
            {
              "name": "Name",
              "datentyp": "VARCHAR",
              "primaerschluessel": false,
              "pflichtfeld": true
            }
          ]
        },
        {
          "name": "Station",
          "attribute": [
            {
              "name": "StationsID",
              "datentyp": "INTEGER",
              "primaerschluessel": true,
              "pflichtfeld": true
            },
            {
              "name": "Name",
              "datentyp": "VARCHAR",
              "primaerschluessel": false,
              "pflichtfeld": true
            },
            {
              "name": "FachbereichID",
              "datentyp": "INTEGER",
              "primaerschluessel": false,
              "pflichtfeld": true
            },
            {
              "name": "Bettenkapazitaet",
              "datentyp": "INTEGER",
              "primaerschluessel": false,
              "pflichtfeld": true
            }
          ]
        },
        {
          "name": "Arzt",
          "attribute": [
            {
              "name": "ArztID",
              "datentyp": "INTEGER",
              "primaerschluessel": true,
              "pflichtfeld": true
            },
            {
              "name": "Vorname",
              "datentyp": "VARCHAR",
              "primaerschluessel": false,
              "pflichtfeld": true
            },
            {
              "name": "Nachname",
              "datentyp": "VARCHAR",
              "primaerschluessel": false,
              "pflichtfeld": true
            },
            {
              "name": "Fachrichtung",
              "datentyp": "VARCHAR",
              "primaerschluessel": false,
              "pflichtfeld": true
            }
          ]
        },
        {
          "name": "Pflegepersonal",
          "attribute": [
            {
              "name": "PersonalID",
              "datentyp": "INTEGER",
              "primaerschluessel": true,
              "pflichtfeld": true
            },
            {
              "name": "Vorname",
              "datentyp": "VARCHAR",
              "primaerschluessel": false,
              "pflichtfeld": true
            },
            {
              "name": "Nachname",
              "datentyp": "VARCHAR",
              "primaerschluessel": false,
              "pflichtfeld": true
            }
          ]
        },
        {
          "name": "Aufenthalt",
          "attribute": [
            {
              "name": "AufenthaltID",
              "datentyp": "INTEGER",
              "primaerschluessel": true,
              "pflichtfeld": true
            },
            {
              "name": "PatientenID",
              "datentyp": "INTEGER",
              "primaerschluessel": false,
              "pflichtfeld": true
            },
            {
              "name": "Aufnahmedatum",
              "datentyp": "DATE",
              "primaerschluessel": false,
              "pflichtfeld": true
            },
            {
              "name": "Aufnahmeuhrzeit",
              "datentyp": "VARCHAR",
              "primaerschluessel": false,
              "pflichtfeld": false
            },
            {
              "name": "Entlassungsdatum",
              "datentyp": "DATE",
              "primaerschluessel": false,
              "pflichtfeld": false
            },
            {
              "name": "Entlassungsuhrzeit",
              "datentyp": "VARCHAR",
              "primaerschluessel": false,
              "pflichtfeld": false
            }
          ]
        },
        {
          "name": "Stationsaufenthalt",
          "attribute": [
            {
              "name": "StationsaufenthaltID",
              "datentyp": "INTEGER",
              "primaerschluessel": true,
              "pflichtfeld": true
            },
            {
              "name": "AufenthaltID",
              "datentyp": "INTEGER",
              "primaerschluessel": false,
              "pflichtfeld": true
            },
            {
              "name": "StationsID",
              "datentyp": "INTEGER",
              "primaerschluessel": false,
              "pflichtfeld": true
            },
            {
              "name": "Anfangsdatum",
              "datentyp": "DATE",
              "primaerschluessel": false,
              "pflichtfeld": true
            },
            {
              "name": "Anfangsuhrzeit",
              "datentyp": "VARCHAR",
              "primaerschluessel": false,
              "pflichtfeld": false
            },
            {
              "name": "Enddatum",
              "datentyp": "DATE",
              "primaerschluessel": false,
              "pflichtfeld": false
            },
            {
              "name": "Enduhrzeit",
              "datentyp": "VARCHAR",
              "primaerschluessel": false,
              "pflichtfeld": false
            }
          ]
        },
        {
          "name": "Behandlungsfall",
          "attribute": [
            {
              "name": "BehandlungsfallID",
              "datentyp": "INTEGER",
              "primaerschluessel": true,
              "pflichtfeld": true
            },
            {
              "name": "PatientenID",
              "datentyp": "INTEGER",
              "primaerschluessel": false,
              "pflichtfeld": true
            },
            {
              "name": "AufenthaltID",
              "datentyp": "INTEGER",
              "primaerschluessel": false,
              "pflichtfeld": false
            },
            {
              "name": "Startdatum",
              "datentyp": "DATE",
              "primaerschluessel": false,
              "pflichtfeld": true
            },
            {
              "name": "Enddatum",
              "datentyp": "DATE",
              "primaerschluessel": false,
              "pflichtfeld": false
            }
          ]
        },
        {
          "name": "Diagnose",
          "attribute": [
            {
              "name": "DiagnoseID",
              "datentyp": "INTEGER",
              "primaerschluessel": true,
              "pflichtfeld": true
            },
            {
              "name": "BehandlungsfallID",
              "datentyp": "INTEGER",
              "primaerschluessel": false,
              "pflichtfeld": true
            },
            {
              "name": "ICDCode",
              "datentyp": "VARCHAR",
              "primaerschluessel": false,
              "pflichtfeld": false
            },
            {
              "name": "Freitext",
              "datentyp": "TEXT",
              "primaerschluessel": false,
              "pflichtfeld": false
            }
          ]
        },
        {
          "name": "Prozedur",
          "attribute": [
            {
              "name": "ProzedurID",
              "datentyp": "INTEGER",
              "primaerschluessel": true,
              "pflichtfeld": true
            },
            {
              "name": "BehandlungsfallID",
              "datentyp": "INTEGER",
              "primaerschluessel": false,
              "pflichtfeld": true
            },
            {
              "name": "ArztID",
              "datentyp": "INTEGER",
              "primaerschluessel": false,
              "pflichtfeld": true
            },
            {
              "name": "OPSCode",
              "datentyp": "VARCHAR",
              "primaerschluessel": false,
              "pflichtfeld": false
            },
            {
              "name": "Beschreibung",
              "datentyp": "TEXT",
              "primaerschluessel": false,
              "pflichtfeld": false
            },
            {
              "name": "Durchfuehrungsdatum",
              "datentyp": "DATE",
              "primaerschluessel": false,
              "pflichtfeld": true
            },
            {
              "name": "Durchfuehrungsuhrzeit",
              "datentyp": "VARCHAR",
              "primaerschluessel": false,
              "pflichtfeld": false
            }
          ]
        },
        {
          "name": "Medikament",
          "attribute": [
            {
              "name": "MedikamentID",
              "datentyp": "INTEGER",
              "primaerschluessel": true,
              "pflichtfeld": true
            },
            {
              "name": "Name",
              "datentyp": "VARCHAR",
              "primaerschluessel": false,
              "pflichtfeld": true
            },
            {
              "name": "Wirkstoff",
              "datentyp": "VARCHAR",
              "primaerschluessel": false,
              "pflichtfeld": false
            }
          ]
        },
        {
          "name": "Medikamentenverordnung",
          "attribute": [
            {
              "name": "VerordnungsID",
              "datentyp": "INTEGER",
              "primaerschluessel": true,
              "pflichtfeld": true
            },
            {
              "name": "BehandlungsfallID",
              "datentyp": "INTEGER",
              "primaerschluessel": false,
              "pflichtfeld": true
            },
            {
              "name": "MedikamentID",
              "datentyp": "INTEGER",
              "primaerschluessel": false,
              "pflichtfeld": true
            },
            {
              "name": "Dosierung",
              "datentyp": "VARCHAR",
              "primaerschluessel": false,
              "pflichtfeld": true
            },
            {
              "name": "Startdatum",
              "datentyp": "DATE",
              "primaerschluessel": false,
              "pflichtfeld": true
            },
            {
              "name": "Enddatum",
              "datentyp": "DATE",
              "primaerschluessel": false,
              "pflichtfeld": false
            }
          ]
        },
        {
          "name": "Termin",
          "attribute": [
            {
              "name": "TerminID",
              "datentyp": "INTEGER",
              "primaerschluessel": true,
              "pflichtfeld": true
            },
            {
              "name": "PatientenID",
              "datentyp": "INTEGER",
              "primaerschluessel": false,
              "pflichtfeld": true
            },
            {
              "name": "Datum",
              "datentyp": "DATE",
              "primaerschluessel": false,
              "pflichtfeld": true
            },
            {
              "name": "Uhrzeit",
              "datentyp": "VARCHAR",
              "primaerschluessel": false,
              "pflichtfeld": true
            },
            {
              "name": "Termintyp",
              "datentyp": "VARCHAR",
              "primaerschluessel": false,
              "pflichtfeld": true
            },
            {
              "name": "Status",
              "datentyp": "VARCHAR",
              "primaerschluessel": false,
              "pflichtfeld": true
            }
          ]
        },
        {
          "name": "PatientArzt",
          "attribute": [
            {
              "name": "PatientArztID",
              "datentyp": "INTEGER",
              "primaerschluessel": true,
              "pflichtfeld": true
            },
            {
              "name": "PatientenID",
              "datentyp": "INTEGER",
              "primaerschluessel": false,
              "pflichtfeld": true
            },
            {
              "name": "ArztID",
              "datentyp": "INTEGER",
              "primaerschluessel": false,
              "pflichtfeld": true
            }
          ]
        },
        {
          "name": "PersonalStation",
          "attribute": [
            {
              "name": "PersonalStationID",
              "datentyp": "INTEGER",
              "primaerschluessel": true,
              "pflichtfeld": true
            },
            {
              "name": "PersonalID",
              "datentyp": "INTEGER",
              "primaerschluessel": false,
              "pflichtfeld": true
            },
            {
              "name": "StationsID",
              "datentyp": "INTEGER",
              "primaerschluessel": false,
              "pflichtfeld": true
            }
          ]
        }
      ],
      "beziehungen": [
        {
          "von": "Patient",
          "zu": "Bezugsperson",
          "kardinalitaet": "1:0..1",
          "beziehungsattribute": []
        },
        {
          "von": "Patient",
          "zu": "Versicherung",
          "kardinalitaet": "1:N",
          "beziehungsattribute": []
        },
        {
          "von": "Versicherung",
          "zu": "Krankenkasse",
          "kardinalitaet": "N:1",
          "beziehungsattribute": []
        },
        {
          "von": "Patient",
          "zu": "Aufenthalt",
          "kardinalitaet": "1:N",
          "beziehungsattribute": []
        },
        {
          "von": "Aufenthalt",
          "zu": "Stationsaufenthalt",
          "kardinalitaet": "1:N",
          "beziehungsattribute": []
        },
        {
          "von": "Stationsaufenthalt",
          "zu": "Station",
          "kardinalitaet": "N:1",
          "beziehungsattribute": []
        },
        {
          "von": "Station",
          "zu": "Fachbereich",
          "kardinalitaet": "N:1",
          "beziehungsattribute": []
        },
        {
          "von": "Patient",
          "zu": "Behandlungsfall",
          "kardinalitaet": "1:N",
          "beziehungsattribute": []
        },
        {
          "von": "Aufenthalt",
          "zu": "Behandlungsfall",
          "kardinalitaet": "1:N",
          "beziehungsattribute": []
        },
        {
          "von": "Behandlungsfall",
          "zu": "Diagnose",
          "kardinalitaet": "1:N",
          "beziehungsattribute": []
        },
        {
          "von": "Behandlungsfall",
          "zu": "Prozedur",
          "kardinalitaet": "1:N",
          "beziehungsattribute": []
        },
        {
          "von": "Prozedur",
          "zu": "Arzt",
          "kardinalitaet": "N:1",
          "beziehungsattribute": []
        },
        {
          "von": "Behandlungsfall",
          "zu": "Medikamentenverordnung",
          "kardinalitaet": "1:N",
          "beziehungsattribute": []
        },
        {
          "von": "Medikamentenverordnung",
          "zu": "Medikament",
          "kardinalitaet": "N:1",
          "beziehungsattribute": []
        },
        {
          "von": "Patient",
          "zu": "Termin",
          "kardinalitaet": "1:N",
          "beziehungsattribute": []
        },
        {
          "von": "Patient",
          "zu": "PatientArzt",
          "kardinalitaet": "1:N",
          "beziehungsattribute": []
        },
        {
          "von": "Arzt",
          "zu": "PatientArzt",
          "kardinalitaet": "1:N",
          "beziehungsattribute": []
        },
        {
          "von": "Pflegepersonal",
          "zu": "PersonalStation",
          "kardinalitaet": "1:N",
          "beziehungsattribute": []
        },
        {
          "von": "Station",
          "zu": "PersonalStation",
          "kardinalitaet": "1:N",
          "beziehungsattribute": []
        }
      ]
    },
    "critic_report": null,
    "critic_report_c1": null,
    "critic_report_c2": null,
    "iteration": 0,
    "max_iter": 3,
    "final_ddl": "CREATE TABLE patients (\n    id INTEGER NOT NULL,\n    firstname VARCHAR(255) NOT NULL,\n    lastname VARCHAR(255) NOT NULL,\n    birthdate DATE NOT NULL,\n    gender VARCHAR(255),\n    address VARCHAR(255),\n    phone VARCHAR(255),\n    email VARCHAR(255),\n    CONSTRAINT pk_patients PRIMARY KEY (id)\n);\n\nCREATE TABLE appointments (\n    id INTEGER NOT NULL,\n    patient_id INTEGER NOT NULL,\n    appointment_date DATE NOT NULL,\n    appointment_time VARCHAR(255) NOT NULL,\n    appointment_type VARCHAR(255) NOT NULL,\n    status VARCHAR(255) NOT NULL,\n    CONSTRAINT pk_appointments PRIMARY KEY (id),\n    CONSTRAINT fk_appointments_patient_id FOREIGN KEY (patient_id) REFERENCES patients (id)\n);\n\nCREATE TABLE contact_persons (\n    id INTEGER NOT NULL,\n    patient_id INTEGER NOT NULL,\n    name VARCHAR(255) NOT NULL,\n    relationship VARCHAR(255),\n    phone VARCHAR(255),\n    email VARCHAR(255),\n    CONSTRAINT pk_contact_persons PRIMARY KEY (id),\n    CONSTRAINT fk_contact_persons_patient_id FOREIGN KEY (patient_id) REFERENCES patients (id)\n);\n\nCREATE TABLE departments (\n    id INTEGER NOT NULL,\n    name VARCHAR(255) NOT NULL,\n    CONSTRAINT pk_departments PRIMARY KEY (id)\n);\n\nCREATE TABLE stays (\n    id INTEGER NOT NULL,\n    patient_id INTEGER NOT NULL,\n    admission_date DATE NOT NULL,\n    admission_time VARCHAR(255),\n    discharge_date DATE,\n    discharge_time VARCHAR(255),\n    CONSTRAINT pk_stays PRIMARY KEY (id),\n    CONSTRAINT fk_stays_patient_id FOREIGN KEY (patient_id) REFERENCES patients (id)\n);\n\nCREATE TABLE treatment_cases (\n    id INTEGER NOT NULL,\n    patient_id INTEGER NOT NULL,\n    stay_id INTEGER,\n    startdate DATE NOT NULL,\n    enddate DATE,\n    CONSTRAINT pk_treatment_cases PRIMARY KEY (id),\n    CONSTRAINT fk_treatment_cases_patient_id FOREIGN KEY (patient_id) REFERENCES patients (id),\n    CONSTRAINT fk_treatment_cases_stay_id FOREIGN KEY (stay_id) REFERENCES stays (id)\n);\n\nCREATE TABLE diagnoses (\n    id INTEGER NOT NULL,\n    treatment_case_id INTEGER NOT NULL,\n    icd_code VARCHAR(255),\n    description TEXT,\n    CONSTRAINT pk_diagnoses PRIMARY KEY (id),\n    CONSTRAINT fk_diagnoses_treatment_case_id FOREIGN KEY (treatment_case_id) REFERENCES treatment_cases (id)\n);\n\nCREATE TABLE insurance_companies (\n    id INTEGER NOT NULL,\n    name VARCHAR(255) NOT NULL,\n    insurance_type VARCHAR(255),\n    CONSTRAINT pk_insurance_companies PRIMARY KEY (id)\n);\n\nCREATE TABLE insurances (\n    id INTEGER NOT NULL,\n    patient_id INTEGER NOT NULL,\n    insurance_company_id INTEGER,\n    startdate DATE NOT NULL,\n    enddate DATE,\n    insurance_type VARCHAR(255) NOT NULL,\n    CONSTRAINT pk_insurances PRIMARY KEY (id),\n    CONSTRAINT fk_insurances_patient_id FOREIGN KEY (patient_id) REFERENCES patients (id),\n    CONSTRAINT fk_insurances_insurance_company_id FOREIGN KEY (insurance_company_id) REFERENCES insurance_companies (id)\n);\n\nCREATE TABLE medications (\n    id INTEGER NOT NULL,\n    name VARCHAR(255) NOT NULL,\n    active_ingredient VARCHAR(255),\n    CONSTRAINT pk_medications PRIMARY KEY (id)\n);\n\nCREATE TABLE medication_prescriptions (\n    id INTEGER NOT NULL,\n    treatment_case_id INTEGER NOT NULL,\n    medication_id INTEGER NOT NULL,\n    dosage VARCHAR(255) NOT NULL,\n    startdate DATE NOT NULL,\n    enddate DATE,\n    CONSTRAINT pk_medication_prescriptions PRIMARY KEY (id),\n    CONSTRAINT fk_medication_prescriptions_treatment_case_id FOREIGN KEY (treatment_case_id) REFERENCES treatment_cases (id),\n    CONSTRAINT fk_medication_prescriptions_medication_id FOREIGN KEY (medication_id) REFERENCES medications (id)\n);\n\nCREATE TABLE nursing_staff (\n    id INTEGER NOT NULL,\n    firstname VARCHAR(255) NOT NULL,\n    lastname VARCHAR(255) NOT NULL,\n    CONSTRAINT pk_nursing_staff PRIMARY KEY (id)\n);\n\nCREATE TABLE stations (\n    id INTEGER NOT NULL,\n    name VARCHAR(255) NOT NULL,\n    department_id INTEGER NOT NULL,\n    bed_capacity INTEGER NOT NULL,\n    CONSTRAINT pk_stations PRIMARY KEY (id),\n    CONSTRAINT fk_stations_department_id FOREIGN KEY (department_id) REFERENCES departments (id)\n);\n\nCREATE TABLE nursing_staff_stations (\n    nursing_staff_id INTEGER NOT NULL,\n    station_id INTEGER NOT NULL,\n    CONSTRAINT pk_nursing_staff_stations PRIMARY KEY (nursing_staff_id, station_id),\n    CONSTRAINT fk_nursing_staff_stations_nursing_staff_id FOREIGN KEY (nursing_staff_id) REFERENCES nursing_staff (id),\n    CONSTRAINT fk_nursing_staff_stations_station_id FOREIGN KEY (station_id) REFERENCES stations (id)\n);\n\nCREATE TABLE physicians (\n    id INTEGER NOT NULL,\n    firstname VARCHAR(255) NOT NULL,\n    lastname VARCHAR(255) NOT NULL,\n    specialization VARCHAR(255) NOT NULL,\n    CONSTRAINT pk_physicians PRIMARY KEY (id)\n);\n\nCREATE TABLE patient_physicians (\n    patient_id INTEGER NOT NULL,\n    physician_id INTEGER NOT NULL,\n    CONSTRAINT pk_patient_physicians PRIMARY KEY (patient_id, physician_id),\n    CONSTRAINT fk_patient_physicians_patient_id FOREIGN KEY (patient_id) REFERENCES patients (id),\n    CONSTRAINT fk_patient_physicians_physician_id FOREIGN KEY (physician_id) REFERENCES physicians (id)\n);\n\nCREATE TABLE procedures (\n    id INTEGER NOT NULL,\n    treatment_case_id INTEGER NOT NULL,\n    physician_id INTEGER NOT NULL,\n    ops_code VARCHAR(255),\n    description TEXT,\n    execution_date DATE NOT NULL,\n    execution_time VARCHAR(255),\n    CONSTRAINT pk_procedures PRIMARY KEY (id),\n    CONSTRAINT fk_procedures_treatment_case_id FOREIGN KEY (treatment_case_id) REFERENCES treatment_cases (id),\n    CONSTRAINT fk_procedures_physician_id FOREIGN KEY (physician_id) REFERENCES physicians (id)\n);\n\nCREATE TABLE station_stays (\n    id INTEGER NOT NULL,\n    stay_id INTEGER NOT NULL,\n    station_id INTEGER NOT NULL,\n    start_date DATE NOT NULL,\n    start_time VARCHAR(255),\n    end_date DATE,\n    end_time VARCHAR(255),\n    CONSTRAINT pk_station_stays PRIMARY KEY (id),\n    CONSTRAINT fk_station_stays_stay_id FOREIGN KEY (stay_id) REFERENCES stays (id),\n    CONSTRAINT fk_station_stays_station_id FOREIGN KEY (station_id) REFERENCES stations (id)\n);\n",
    "final_critic_report": null,
    "error": null,
    "diskussionsverlauf": []
  },
  "telemetry": {
    "total_calls": 3,
    "total_input_tokens": 15684,
    "total_output_tokens": 12738,
    "total_tokens": 28422,
    "total_cost_usd": 0.0,
    "per_agent": {
      "requirements_analyst": {
        "calls": 1,
        "input_tokens": 1893,
        "output_tokens": 3263,
        "cost_usd": 0.0
      },
      "conceptual_model_designer": {
        "calls": 1,
        "input_tokens": 5413,
        "output_tokens": 4879,
        "cost_usd": 0.0
      },
      "logical_schema_designer": {
        "calls": 1,
        "input_tokens": 8378,
        "output_tokens": 4596,
        "cost_usd": 0.0
      }
    },
    "calls": [
      {
        "workflow_name": "ps",
        "iteration": 0,
        "agent_name": "requirements_analyst",
        "model": "claude-haiku-4-5-20251001",
        "input_tokens": 1893,
        "output_tokens": 3263,
        "cost_usd": 0.0
      },
      {
        "workflow_name": "ps",
        "iteration": 0,
        "agent_name": "conceptual_model_designer",
        "model": "claude-haiku-4-5-20251001",
        "input_tokens": 5413,
        "output_tokens": 4879,
        "cost_usd": 0.0
      },
      {
        "workflow_name": "ps",
        "iteration": 0,
        "agent_name": "logical_schema_designer",
        "model": "claude-haiku-4-5-20251001",
        "input_tokens": 8378,
        "output_tokens": 4596,
        "cost_usd": 0.0
      }
    ]
  }
}